icon_mapping_pkg_/__init__.py
icon_mapping_pkg_/weather_icons.py
weathericonsmapping-0.1.0.dist-info/METADATA
weathericonsmapping-0.1.0.dist-info/WHEEL
weathericonsmapping-0.1.0.dist-info/top_level.txt
weathericonsmapping-0.1.0.dist-info/RECORD
