Metadata-Version: 2.4
Name: WeatherIconsMapping
Version: 0.1.0
Summary:  Package to map weather icons to weather descriptions
Home-page: https://github.com/pypa/sampleproject
Author: Balaji Srikanthan
Author-email: balaji.sbca2020@gmail.com
Classifier: Programming Language :: Python :: 3
Classifier: License :: OSI Approved :: MIT License
Classifier: Operating System :: OS Independent
Requires-Python: >=3.6
Dynamic: author
Dynamic: author-email
Dynamic: classifier
Dynamic: description-content-type
Dynamic: home-page
Dynamic: requires-python
Dynamic: summary
